LICENSE
README.md
setup.cfg
setup.py
doc_fzf/__init__.py
doc_fzf/cache.py
doc_fzf/main.py
doc_fzf/pyfzf.py
doc_fzf.egg-info/PKG-INFO
doc_fzf.egg-info/SOURCES.txt
doc_fzf.egg-info/dependency_links.txt
doc_fzf.egg-info/entry_points.txt
doc_fzf.egg-info/requires.txt
doc_fzf.egg-info/top_level.txt
doc_fzf/modules/__init__.py
doc_fzf/modules/ansible.py
doc_fzf/modules/python.py
doc_fzf/modules/terraform.py