Metadata-Version: 2.1
Name: doc-fzf
Version: 0.0.7
Summary: Fuzzy Search documentation from the CLI
Home-page: https://gitlab.com/memogarcia/doc-fzf
Author: Guillermo Garcia
Author-email: memogarcia@protonmail.com
License: WTFPL
Keywords: documentation fzf fuzzy search
Platform: UNKNOWN
Classifier: Intended Audience :: Developers
Classifier: Intended Audience :: System Administrators
Classifier: Natural Language :: English
Classifier: Programming Language :: Python
Classifier: Programming Language :: Python :: 3
Classifier: Programming Language :: Python :: 3.5
Classifier: Programming Language :: Python :: 3.6
Classifier: Programming Language :: Python :: 3.7
Classifier: Programming Language :: Python :: Implementation :: CPython
